{
  "datatable": [
    {
      "id": 1,
      "actual_name": "unit1",
      "short_name": "unit1",
      "allow_decimal": "u1d",
      "base_unit_id": null,
      "base_unit_multiplier": null,
      "base_unit": null
    },
    {
      "id": 2,
      "actual_name": "unit1",
      "short_name": "unit1",
      "allow_decimal": "u1d",
      "base_unit_id": null,
      "base_unit_multiplier": null,
      "base_unit": null
    },
    {
      "id": 3,
      "actual_name": "unit1",
      "short_name": "unit1",
      "allow_decimal": "u1d",
      "base_unit_id": null,
      "base_unit_multiplier": null,
      "base_unit": null
    },
    {
      "id": 4,
      "actual_name": "unit1",
      "short_name": "unit1",
      "allow_decimal": "u1d",
      "base_unit_id": null,
      "base_unit_multiplier": null,
      "base_unit": null
    },
    {
      "actual_name": "111111114",
      "short_name": "22222222",
      "allow_decimal": "3333333",
      "id": 7
    },
    {
      "actual_name": "rrr666",
      "short_name": "rrrr666",
      "allow_decimal": "rrrr666",
      "id": 8
    },
    {
      "actual_name": "dwd",
      "short_name": "dwd",
      "allow_decimal": "SDSD",
      "id": 9
    },
    {
      "actual_name": "dawsd",
      "short_name": "sdas",
      "allow_decimal": "sfasf",
      "id": 10
    },
    {
      "actual_name": "we",
      "short_name": "we",
      "allow_decimal": "atrt",
      "id": 11
    }
  ]
}